pybuildingenergy/__init__.py
pybuildingenergy/global_inputs.py
pybuildingenergy/pybuildingenergy.py
pybuildingenergy/data/building_archetype.py
pybuildingenergy/source/DHW.py
pybuildingenergy/source/__init__.py
pybuildingenergy/source/functions.py
pybuildingenergy/source/graphs.py
pybuildingenergy/source/utils.py
pybuildingenergy-1.0.7.dist-info/METADATA
pybuildingenergy-1.0.7.dist-info/WHEEL
pybuildingenergy-1.0.7.dist-info/top_level.txt
pybuildingenergy-1.0.7.dist-info/RECORD
