Metadata-Version: 2.1
Name: pybuildingenergy
Version: 1.0.7
Summary: Energy Simulation of building usin ISO52016 and more
Home-page: https://github.com/EURAC-EEBgroup/pyBuildingEnergy
Author: Daniele Antonucci
Author-email: Daniele Antonucci <daniele.antonucci@eurac.edu>
Maintainer-email: Daniele Antonucci <daniele.antonucci@eurac.edu>
License: MIT License
Project-URL: Homepage, https://github.com/EURAC-EEBgroup/pyBuildingEnergy
Project-URL: Documentation, https://pybuildingenergy.readthedocs.io/en/latest/Overview/overview.html
Project-URL: Repository, https://github.com/EURAC-EEBgroup/pyBuildingEnergy
Project-URL: Issues, https://github.com/EURAC-EEBgroup/pyBuildingEnergy/issues
Project-URL: Changelog, https://github.com/EURAC-EEBgroup/pyBuildingEnergy/CHANGELOG.md
Keywords: energy,building,heating and cooling,52016,EPBD
Classifier: Development Status :: 4 - Beta
Classifier: Intended Audience :: Developers
Classifier: Intended Audience :: Education
Classifier: Intended Audience :: Science/Research
Classifier: Operating System :: Unix
Classifier: Operating System :: POSIX
Classifier: Operating System :: Microsoft :: Windows
Classifier: License :: OSI Approved :: MIT License
Classifier: Programming Language :: Python :: 3
Classifier: Programming Language :: Python :: 3.8
Classifier: Programming Language :: Python :: 3.9
Classifier: Programming Language :: Python :: 3.10
Classifier: Programming Language :: Python :: 3.11
Classifier: Topic :: Scientific/Engineering
Classifier: Topic :: Software Development :: Build Tools
Requires-Python: >=3.8.0
Requires-Dist: bump2version ==0.5.11
Requires-Dist: coverage ==4.5.4
Requires-Dist: pandas >=2.0.3
Requires-Dist: numpy ==1.23.2
Requires-Dist: DateTime ==5.1
Requires-Dist: timezonefinder ==6.2.0
Requires-Dist: requests ==2.31.0
Requires-Dist: tqdm ==4.66.1
Requires-Dist: Pyarrow ==13.0.0
Requires-Dist: pyecharts ==2.0.4
Requires-Dist: geopy ==2.4.1
Requires-Dist: pvlib ==0.10.1
Requires-Dist: scikit-learn >=1.3.2
Requires-Dist: urllib3 ==1.26.18
Requires-Dist: pyswarms ==1.3.0
Requires-Dist: workalendar ==17.0.0
Requires-Dist: plotly ==5.21.0
Provides-Extra: cli
Provides-Extra: gui
Provides-Extra: testing
Requires-Dist: setuptools ; extra == 'testing'
Requires-Dist: pytest ; extra == 'testing'
Requires-Dist: pytest-cov ; extra == 'testing'
